feelpp/__init__.py
feelpp/mo2fmu/__init__.py
feelpp/mo2fmu/mo2fmu.py
feelpp/mo2fmu/py.typed
feelpp_mo2fmu-0.5.2.dist-info/licenses/LICENSE
feelpp_mo2fmu-0.5.2.dist-info/METADATA
feelpp_mo2fmu-0.5.2.dist-info/WHEEL
feelpp_mo2fmu-0.5.2.dist-info/entry_points.txt
feelpp_mo2fmu-0.5.2.dist-info/top_level.txt
feelpp_mo2fmu-0.5.2.dist-info/RECORD
