Metadata-Version: 2.4
Name: feelpp-mo2fmu
Version: 0.5.2
Summary: Feel++ modelica to fmu converter package
Author-email: Christophe Prud'homme <christophe.prudhomme@cemosis.fr>, Philippe Pinçon <philippe.pincon@cemosis.fr>
License: MIT
Project-URL: Homepage, https://feelpp.github.io/mo2fmu
Project-URL: Documentation, https://feelpp.github.io/mo2fmu
Project-URL: Repository, https://github.com/feelpp/mo2fmu
Project-URL: Issues, https://github.com/feelpp/mo2fmu/issues
Keywords: modelica,fmu,fmi,dymola,simulation
Classifier: Development Status :: 4 - Beta
Classifier: Intended Audience :: Science/Research
Classifier: Intended Audience :: Developers
Classifier: Programming Language :: Python :: 3
Classifier: Programming Language :: Python :: 3.9
Classifier: Programming Language :: Python :: 3.10
Classifier: Programming Language :: Python :: 3.11
Classifier: Programming Language :: Python :: 3.12
Classifier: Programming Language :: Python :: 3.13
Classifier: Programming Language :: Python :: 3 :: Only
Classifier: Operating System :: OS Independent
Classifier: Topic :: Scientific/Engineering
Requires-Python: >=3.8.1
License-File: LICENSE
Requires-Dist: click
Requires-Dist: spdlog
Requires-Dist: xvfbwrapper
Requires-Dist: pathlib
Provides-Extra: test
Requires-Dist: pytest>=7.0; extra == "test"
Requires-Dist: pytest-cov>=4.0; extra == "test"
Provides-Extra: dev
Requires-Dist: pipx; extra == "dev"
Requires-Dist: build; extra == "dev"
Requires-Dist: twine; extra == "dev"
Provides-Extra: lint
Requires-Dist: black>=23.0; extra == "lint"
Requires-Dist: flake8>=6.0; extra == "lint"
Requires-Dist: flake8-docstrings>=1.7; extra == "lint"
Requires-Dist: flake8-bugbear>=23.0; extra == "lint"
Requires-Dist: mypy>=1.0; extra == "lint"
Requires-Dist: ruff>=0.1.0; extra == "lint"
Requires-Dist: isort>=5.12; extra == "lint"
Provides-Extra: all
Requires-Dist: feelpp-mo2fmu[dev,lint,test]; extra == "all"
Dynamic: license-file
